PARTE 1/Numero.v
module Numero(A, B, C, D, d1, d2, d3, d4, d5, reset, ready);//parametros
	input wire A, B, C, D, reset, ready;//entradas como fios, já que vão passar os valores para a equação
	output reg d1, d2, d3, d4, d5;//saidas como registradores, já que irão guardar os valores da equação
	always @(reset) begin//bloco always que é executado sempre quando o reset for 1
		d1 <= 0;
		d2 <= 0;
		d3 <= 0;
		d4 <= 0;
		d5 <= 0;
	end//fim do bloco always
	always @(ready) begin//bloco always que é executado sempre quando o ready for 1
		if(~reset) begin//só executa quando o ready for 1 e o reset for 0
			d5 <= (B & ~C) | (~A & ~C & D) | (~B & C);//display 5 com sua equacao
			d4 <= (B & ~C) | (~B & C) | (C & ~D);//display 4 com sua equacao
			d3 <= (B) | (C & D);//display 3 com sua equacao
			d2 <= (B) | (A & ~C & ~D);//display 2 com sua equacao
			d1 <= (A) | (B & D) | (B & C);//display 1 com sua equacao
		end//fim da condição
	end//fim bloco always
endmodule//fim modulo

PARTE 1/testbench.v
`include "Numero.v"//incluíndo o modulo com as equações a serem usadas
module testbench();//modulo da simulacao
	reg A, B, C, D, reset, ready;//definindo as entradas como registradores para guardar os valores
	wire d1, d2, d3, d4, d5;//definindo as saídas como fios para passarem os valores
	Numero moduloNumero (.A(A), .B(B), .C(C), .D(D), .d1(d1), .d2(d2), .d3(d3), .d4(d4), .d5(d5), .reset(reset), .ready(ready));//instanciando o módulo das equações
	initial begin//começo do bloco initial
		$dumpfile("Numero.vcd");//criando o arquivo vcd para gerar a forma de onda
		$dumpvars(0, testbench);//definindo todas as variaveis como 0
		$display("Conversao para codigo morse:");//exibindo na tela
		$monitor("%b%b%b%b = %b%b%b%b%b", A, B, C, D, d5, d4, d3, d2, d1);//acompanhando cada mudança nas variaveis e exibindo na tela
	end//fim do bloco initial
	initial begin//começo do bloco initial
			reset = 1;//usando o reset para começar a simulação
		#1; reset = 0;//indicando que já pode colocar valores
		//as linhas seguintes definem a tabela da verdade e as alterações no ready indicando que já pode fazer a conversão quando o mesmo for 1
		#1; ready = 0; A = 0; B = 0; C = 0; D = 0; ready = 1;
		#1; ready = 0; A = 0; B = 0; C = 0; D = 1; ready = 1;
		#1; ready = 0; A = 0; B = 0; C = 1; D = 0; ready = 1;
		#1; ready = 0; A = 0; B = 0; C = 1; D = 1; ready = 1;
		#1; ready = 0; A = 0; B = 1; C = 0; D = 0; ready = 1;
		#1; ready = 0; A = 0; B = 1; C = 0; D = 1; ready = 1;
		#1; ready = 0; A = 0; B = 1; C = 1; D = 0; ready = 1;
		#1; ready = 0; A = 0; B = 1; C = 1; D = 1; ready = 1;
		#1; ready = 0; A = 1; B = 0; C = 0; D = 0; ready = 1;
		#1; ready = 0; A = 1; B = 0; C = 0; D = 1; ready = 1;
		#1;//fim da simulação
		$finish;//fim das operações do primeiro bloco initial
	end//fim do bloco initial
endmodule//fim do modulo

PARTE 1/Numero.vcd
$date
	Fri Sep 28 09:56:14 2018
$end
$version
	Icarus Verilog
$end
$timescale
	1s
$end
$scope module testbench $end
$var wire 1 ! d5 $end
$var wire 1 " d4 $end
$var wire 1 # d3 $end
$var wire 1 $ d2 $end
$var wire 1 % d1 $end
$var reg 1 & A $end
$var reg 1 ' B $end
$var reg 1 ( C $end
$var reg 1 ) D $end
$var reg 1 * ready $end
$var reg 1 + reset $end
$scope module moduloNumero $end
$var wire 1 & A $end
$var wire 1 ' B $end
$var wire 1 ( C $end
$var wire 1 ) D $end
$var wire 1 * ready $end
$var wire 1 + reset $end
$var reg 1 % d1 $end
$var reg 1 $ d2 $end
$var reg 1 # d3 $end
$var reg 1 " d4 $end
$var reg 1 ! d5 $end
$upscope $end
$upscope $end
$enddefinitions $end
#0
$dumpvars
1+
x*
x)
x(
x'
x&
0%
0$
0#
0"
0!
$end
#1
0+
#2
0)
0(
0'
0&
1*
#3
1!
1)
1*
#4
1"
0)
1(
1*
#5
1#
1)
1*
#6
1$
0)
0(
1'
1*
#7
1%
1)
1*
#8
0!
0)
1(
1*
#9
0"
1)
1*
#10
0#
0)
0(
0'
1&
1*
#11
0$
1)
1*
